<?xml version="1.0" encoding="UTF-8"?>
<ref id="CR24" class="ref">
 <span class="label" xmlns="http://www.w3.org/1999/xhtml">24.</span>
 <element-citation publication-type="journal" class="element-citation">
  <person-group person-group-type="author" class="person-group">
   <name class="name">
    <span class="surname" xmlns="http://www.w3.org/1999/xhtml">Clauset</span>
    <span class="given-names" xmlns="http://www.w3.org/1999/xhtml">A</span>
   </name>
   <name class="name">
    <span class="surname" xmlns="http://www.w3.org/1999/xhtml">Shalizi</span>
    <span class="given-names" xmlns="http://www.w3.org/1999/xhtml">CR</span>
   </name>
   <name class="name">
    <span class="surname" xmlns="http://www.w3.org/1999/xhtml">Newman</span>
    <span class="given-names" xmlns="http://www.w3.org/1999/xhtml">MEJ</span>
   </name>
  </person-group>
  <div class="article-title" xmlns="http://www.w3.org/1999/xhtml">Power law distributions in empirical data</div>
  <div class="source" xmlns="http://www.w3.org/1999/xhtml">SIAM Review</div>
  <span class="year" xmlns="http://www.w3.org/1999/xhtml">2009</span>
  <span class="volume" xmlns="http://www.w3.org/1999/xhtml">51</span>
  <span class="fpage" xmlns="http://www.w3.org/1999/xhtml">661</span>
  <span class="lpage" xmlns="http://www.w3.org/1999/xhtml">703</span>
  <span pub-id-type="doi" class="pub-id" xmlns="http://www.w3.org/1999/xhtml">10.1137/070710111</span>
 </element-citation>
</ref>
