<?xml version="1.0" encoding="UTF-8"?>
<ref id="B65-ijerph-13-00889" class="ref">
 <label class="label">65.</label>
 <element-citation publication-type="book" class="element-citation">
  <person-group person-group-type="author" class="person-group">
   <name class="name">
    <surname class="surname">Hay</surname>
    <given-names class="given-names">I.</given-names>
   </name>
  </person-group>
  <source class="source">Qualitative Research Methods in Human Geography</source>
  <publisher-name class="publisher-name">Oxford University Press</publisher-name>
  <publisher-loc class="publisher-loc">South Melbourne, Australia</publisher-loc>
  <year class="year">2005</year>
 </element-citation>
</ref>
