{
  "id": [
    "21738434"
  ],
  "source": [
    "MED"
  ],
  "pmid": [
    "21738434"
  ],
  "pmcid": [
    "PMC3131038"
  ],
  "doi": [
    "10.3897/zookeys.100.1547"
  ],
  "title": [
    "Animals as an indicator of carbon sequestration and valuable landscapes."
  ],
  "authorString": [
    "Szyszko J, Schwerk A, Malczyk J."
  ],
  "authorList": [
    {
      "author": [
        {
          "fullName": [
            "Szyszko J"
          ],
          "firstName": [
            "Jan"
          ],
          "lastName": [
            "Szyszko"
          ],
          "initials": [
            "J"
          ]
        },
        {
          "fullName": [
            "Schwerk A"
          ],
          "firstName": [
            "Axel"
          ],
          "lastName": [
            "Schwerk"
          ],
          "initials": [
            "A"
          ],
          "authorId": [
            {
              "_": "0000-0002-2284-3776",
              "$": {
                "type": "ORCID"
              }
            }
          ]
        },
        {
          "fullName": [
            "Malczyk J"
          ],
          "firstName": [
            "Jarosław"
          ],
          "lastName": [
            "Malczyk"
          ],
          "initials": [
            "J"
          ]
        }
      ]
    }
  ],
  "authorIdList": [
    {
      "authorId": [
        {
          "_": "0000-0002-2284-3776",
          "$": {
            "type": "ORCID"
          }
        }
      ]
    }
  ],
  "journalInfo": [
    {
      "issue": [
        "100"
      ],
      "journalIssueId": [
        "1846763"
      ],
      "dateOfPublication": [
        "2011 "
      ],
      "monthOfPublication": [
        "0"
      ],
      "yearOfPublication": [
        "2011"
      ],
      "printPublicationDate": [
        "2011-01-01"
      ],
      "journal": [
        {
          "title": [
            "ZooKeys"
          ],
          "ISOAbbreviation": [
            "Zookeys"
          ],
          "medlineAbbreviation": [
            "Zookeys"
          ],
          "NLMid": [
            "101497933"
          ],
          "ISSN": [
            "1313-2989"
          ],
          "ESSN": [
            "1313-2970"
          ]
        }
      ]
    }
  ],
  "pubYear": [
    "2011"
  ],
  "pageInfo": [
    "565-573"
  ],
  "abstractText": [
    "Possibilities of the assessment of a landscape with the use of succession development stages, monitored with the value of the Mean Individual Biomass (MIB) of carabid beetles and the occurrence of bird species are discussed on the basis of an example from Poland. Higher variability of the MIB value in space signifies a greater biodiversity. Apart from the variability of MIB, it is suggested to adopt the occurrence of the following animals as indicators, (in the order of importance), representing underlying valuable landscapes: black stork, lesser spotted eagle, white-tailed eagle, wolf, crane and white stork. The higher number of these species and their greater density indicate a higher value of the landscape for biodiversity and ecosystem services, especially carbon sequestration. All these indicators may be useful to assess measures for sustainable land use."
  ],
  "language": [
    "eng"
  ],
  "pubModel": [
    "Print-Electronic"
  ],
  "pubTypeList": [
    {
      "pubType": [
        "research-article",
        "Journal Article"
      ]
    }
  ],
  "keywordList": [
    {
      "keyword": [
        "Carabidae",
        "Indicators",
        "Mean Individual Biomass (Mib)",
        "Landscape Evaluation"
      ]
    }
  ],
  "fullTextUrlList": [
    {
      "fullTextUrl": [
        {
          "availability": [
            "Open access"
          ],
          "availabilityCode": [
            "OA"
          ],
          "documentStyle": [
            "pdf"
          ],
          "site": [
            "Europe_PMC"
          ],
          "url": [
            "http://europepmc.org/articles/PMC3131038?pdf=render"
          ]
        },
        {
          "availability": [
            "Open access"
          ],
          "availabilityCode": [
            "OA"
          ],
          "documentStyle": [
            "html"
          ],
          "site": [
            "Europe_PMC"
          ],
          "url": [
            "http://europepmc.org/articles/PMC3131038"
          ]
        },
        {
          "availability": [
            "Free"
          ],
          "availabilityCode": [
            "F"
          ],
          "documentStyle": [
            "pdf"
          ],
          "site": [
            "PubMedCentral"
          ],
          "url": [
            "https://www.ncbi.nlm.nih.gov/pmc/articles/pmid/21738434/pdf/?tool=EBI"
          ]
        },
        {
          "availability": [
            "Free"
          ],
          "availabilityCode": [
            "F"
          ],
          "documentStyle": [
            "html"
          ],
          "site": [
            "PubMedCentral"
          ],
          "url": [
            "https://www.ncbi.nlm.nih.gov/pmc/articles/pmid/21738434/?tool=EBI"
          ]
        },
        {
          "availability": [
            "Subscription required"
          ],
          "availabilityCode": [
            "S"
          ],
          "documentStyle": [
            "doi"
          ],
          "site": [
            "DOI"
          ],
          "url": [
            "https://doi.org/10.3897/zookeys.100.1547"
          ]
        }
      ]
    }
  ],
  "isOpenAccess": [
    "Y"
  ],
  "inEPMC": [
    "Y"
  ],
  "inPMC": [
    "Y"
  ],
  "hasPDF": [
    "Y"
  ],
  "hasBook": [
    "N"
  ],
  "hasSuppl": [
    "N"
  ],
  "citedByCount": [
    "0"
  ],
  "hasReferences": [
    "Y"
  ],
  "hasTextMinedTerms": [
    "Y"
  ],
  "hasDbCrossReferences": [
    "N"
  ],
  "hasLabsLinks": [
    "Y"
  ],
  "license": [
    "cc by"
  ],
  "authMan": [
    "N"
  ],
  "epmcAuthMan": [
    "N"
  ],
  "nihAuthMan": [
    "N"
  ],
  "hasTMAccessionNumbers": [
    "N"
  ],
  "dateOfCompletion": [
    "2011-07-14"
  ],
  "dateOfCreation": [
    "2011-07-08"
  ],
  "firstIndexDate": [
    "2011-07-09"
  ],
  "dateOfRevision": [
    "2013-05-29"
  ],
  "electronicPublicationDate": [
    "2011-05-20"
  ],
  "firstPublicationDate": [
    "2011-05-20"
  ]
}