<?xml version="1.0" encoding="UTF-8"?>
<fig id="fig04" fig-type="figure" orientation="portrait" position="float" class="fig">
 <label class="label">Fig. 4.</label>
 <caption class="caption">
  <p class="p">Signal, noise, and S/N ratios from a pattern-based fingerprint analysis of annual-mean atmospheric temperature changes in the CanESM2 ALL ensemble and in satellite data. Results are for TLS (
   <italic class="italic">A</italic>, 
   <italic class="italic">C</italic>, and 
   <italic class="italic">E</italic>) and TMT (
   <italic class="italic">B</italic>, 
   <italic class="italic">D</italic>, and 
   <italic class="italic">F</italic>) and are a function of the trend length 
   <inline-formula class="inline-formula">
    <math id="i36" class="math">
     <mi class="mi">L</mi>
    </math>
   </inline-formula>. The domain is near global (
   <inline-formula class="inline-formula">
    <math id="i37" class="math">
     <mn class="mn">8</mn>
     <msup class="msup">
      <mrow class="mrow">
       <mn class="mn">0</mn>
      </mrow>
      <mrow class="mrow">
       <mo class="mo">○</mo>
      </mrow>
     </msup>
    </math>
   </inline-formula>N to 
   <inline-formula class="inline-formula">
    <math id="i38" class="math">
     <mn class="mn">8</mn>
     <msup class="msup">
      <mrow class="mrow">
       <mn class="mn">0</mn>
      </mrow>
      <mrow class="mrow">
       <mo class="mo">○</mo>
      </mrow>
     </msup>
    </math>
   </inline-formula>S for TLS and TMT). For definition of signal trends (
   <italic class="italic">A</italic> and 
   <italic class="italic">B</italic>) and the standard deviation of the sampling distribution of noise trends (
   <italic class="italic">C</italic> and 
   <italic class="italic">D</italic>), refer to 
   <xref ref-type="sec" rid="s7" class="xref">
    <italic class="italic">Materials and Methods</italic>
   </xref>.
  </p>
 </caption>
 <graphic id="gra4" xlink:href="pnas.1904586116fig04" class="graphic" xmlns:xlink="http://www.w3.org/1999/xlink"/>
</fig>
