<?xml version="1.0" encoding="UTF-8"?>
<contrib-group class="contrib-group">
 <contrib contrib-type="author" class="contrib">
  <contrib-id contrib-id-type="orcid" authenticated="true" class="contrib-id">https://orcid.org/0000-0003-4897-2012</contrib-id>
  <name class="name">
   <surname class="surname">Yu</surname>
   <given-names class="given-names">Qibiao</given-names>
  </name>
  <xref ref-type="aff" rid="af1-ijerph-15-02734" class="xref">1</xref>
  <xref ref-type="aff" rid="af2-ijerph-15-02734" class="xref">2</xref>
 </contrib>
 <contrib contrib-type="author" class="contrib">
  <name class="name">
   <surname class="surname">Wang</surname>
   <given-names class="given-names">Fang</given-names>
  </name>
  <xref ref-type="aff" rid="af1-ijerph-15-02734" class="xref">1</xref>
 </contrib>
 <contrib contrib-type="author" class="contrib">
  <contrib-id contrib-id-type="orcid" authenticated="true" class="contrib-id">https://orcid.org/0000-0002-9660-4436</contrib-id>
  <name class="name">
   <surname class="surname">Yan</surname>
   <given-names class="given-names">Weijin</given-names>
  </name>
  <xref ref-type="aff" rid="af1-ijerph-15-02734" class="xref">1</xref>
  <xref rid="c1-ijerph-15-02734" ref-type="corresp" class="xref">*</xref>
 </contrib>
 <contrib contrib-type="author" class="contrib">
  <name class="name">
   <surname class="surname">Zhang</surname>
   <given-names class="given-names">Fengsong</given-names>
  </name>
  <xref ref-type="aff" rid="af1-ijerph-15-02734" class="xref">1</xref>
  <xref rid="c1-ijerph-15-02734" ref-type="corresp" class="xref">*</xref>
 </contrib>
 <contrib contrib-type="author" class="contrib">
  <name class="name">
   <surname class="surname">Lv</surname>
   <given-names class="given-names">Shucong</given-names>
  </name>
  <xref ref-type="aff" rid="af1-ijerph-15-02734" class="xref">1</xref>
 </contrib>
 <contrib contrib-type="author" class="contrib">
  <name class="name">
   <surname class="surname">Li</surname>
   <given-names class="given-names">Yanqiang</given-names>
  </name>
  <xref ref-type="aff" rid="af1-ijerph-15-02734" class="xref">1</xref>
 </contrib>
</contrib-group>
