<?xml version="1.0" encoding="UTF-8"?>
<ref id="CR66" class="ref">
 <element-citation publication-type="journal" class="element-citation">
  <person-group person-group-type="author" class="person-group">
   <name class="name">
    <span class="surname" xmlns="http://www.w3.org/1999/xhtml">Pain</span>
    <span class="given-names" xmlns="http://www.w3.org/1999/xhtml">DJ</span>
   </name>
   <name class="name">
    <span class="surname" xmlns="http://www.w3.org/1999/xhtml">Meharg</span>
    <span class="given-names" xmlns="http://www.w3.org/1999/xhtml">AA</span>
   </name>
   <name class="name">
    <span class="surname" xmlns="http://www.w3.org/1999/xhtml">Ferrer</span>
    <span class="given-names" xmlns="http://www.w3.org/1999/xhtml">M</span>
   </name>
   <name class="name">
    <span class="surname" xmlns="http://www.w3.org/1999/xhtml">Taggart</span>
    <span class="given-names" xmlns="http://www.w3.org/1999/xhtml">M</span>
   </name>
   <name class="name">
    <span class="surname" xmlns="http://www.w3.org/1999/xhtml">Penteriani</span>
    <span class="given-names" xmlns="http://www.w3.org/1999/xhtml">V</span>
   </name>
  </person-group>
  <div class="article-title" xmlns="http://www.w3.org/1999/xhtml">Lead concentrations in bones and feathers of the globally threatened Spanish imperial eagle</div>
  <div class="source" xmlns="http://www.w3.org/1999/xhtml">Biol Conserv</div>
  <span class="year" xmlns="http://www.w3.org/1999/xhtml">2005</span>
  <span class="volume" xmlns="http://www.w3.org/1999/xhtml">121</span>
  <span class="fpage" xmlns="http://www.w3.org/1999/xhtml">603</span>
  <span class="lpage" xmlns="http://www.w3.org/1999/xhtml">661</span>
  <span pub-id-type="doi" class="pub-id" xmlns="http://www.w3.org/1999/xhtml">10.1016/j.biocon.2004.06.012</span>
 </element-citation>
</ref>
