<?xml version="1.0" encoding="UTF-8"?>
<ref id="eva12803-bib-0004" class="ref">
 <div publication-type="journal" id="eva12803-cit-0004" class="mixed-citation" xmlns="http://www.w3.org/1999/xhtml">
  <div class="string-name">
   <span class="surname">Anderson</span>, 
   <span class="given-names">J. T.</span>
  </div>, 
  <div class="string-name">
   <span class="surname">Inouye</span>, 
   <span class="given-names">D. W.</span>
  </div>, 
  <div class="string-name">
   <span class="surname">McKinney</span>, 
   <span class="given-names">A. M.</span>
  </div>, 
  <div class="string-name">
   <span class="surname">Colautti</span>, 
   <span class="given-names">R. I.</span>
  </div>, &amp; 
  <div class="string-name">
   <span class="surname">Mitchell‐Olds</span>, 
   <span class="given-names">T.</span>
  </div> (
  <span class="year">2012</span>). 
  <div class="article-title">Phenotypic plasticity and adaptive evolution contribute to advancing flowering phenology in response to climate change</div>. 
  <div xml:lang="en" class="source">Proceedings of the Royal Society of London B: Biological Sciences</div>, 
  <span class="volume">279</span>(
  <span class="issue">1743</span>), 
  <span class="fpage">3843</span>–
  <span class="lpage">3852</span>. 
  <span pub-id-type="doi" class="pub-id">10.1098/rspb.2012.1051</span>
 </div>
</ref>
