<?xml version="1.0" encoding="UTF-8"?>
<ref id="CIT0007">
 <mixed-citation publication-type="book">
  <person-group person-group-type="author">
   <name name-style="western">
    <surname>Chanza</surname>
    <given-names>N</given-names>
   </name>. &amp; 
   <name name-style="western">
    <surname>Ayal</surname>
    <given-names>D.Y</given-names>
   </name>.
  </person-group>, 
  <year>2014</year>, 
  <source>
   <italic toggle="yes">Local knowledge contributes to adaptation success</italic>
  </source>, 
  <publisher-name>Joto Afrika</publisher-name>, 
  <publisher-loc>Alin</publisher-loc>.
 </mixed-citation>
</ref>
