<?xml version="1.0" encoding="UTF-8"?>
<results title="frequencies">
 <result title="frequency" word="team" count="114"/>
 <result title="frequency" word="Team" count="71"/>
 <result title="frequency" word="teams" count="51"/>
 <result title="frequency" word="improvement" count="39"/>
 <result title="frequency" word="performance" count="31"/>
 <result title="frequency" word="quality" count="28"/>
 <result title="frequency" word="staff" count="28"/>
 <result title="frequency" word="members" count="27"/>
 <result title="frequency" word="ATPI" count="22"/>
 <result title="frequency" word="{border-style" count="20"/>
 <result title="frequency" word="average" count="18"/>
 <result title="frequency" word="care" count="18"/>
 <result title="frequency" word="px;}" count="18"/>
 <result title="frequency" word="#ffffff;}" count="17"/>
 <result title="frequency" word="Health" count="17"/>
 <result title="frequency" word="work" count="17"/>
 <result title="frequency" word="scores" count="15"/>
 <result title="frequency" word="provided" count="13"/>
 <result title="frequency" word="teams." count="13"/>
 <result title="frequency" word="clinical" count="12"/>
 <result title="frequency" word="improvements" count="12"/>
 <result title="frequency" word="project" count="12"/>
 <result title="frequency" word="support" count="12"/>
 <result title="frequency" word="working" count="12"/>
 <result title="frequency" word="patient" count="11"/>
 <result title="frequency" word="patients" count="11"/>
 <result title="frequency" word="reported" count="11"/>
 <result title="frequency" word="Quality" count="10"/>
 <result title="frequency" word="project." count="10"/>
 <result title="frequency" word="teamwork" count="10"/>
 <result title="frequency" word="team’s" count="10"/>
 <result title="frequency" word="NHS" count="9"/>
 <result title="frequency" word="effects" count="9"/>
 <result title="frequency" word="health" count="9"/>
 <result title="frequency" word="repeat" count="9"/>
 <result title="frequency" word="time" count="9"/>
 <result title="frequency" word="Performance" count="8"/>
 <result title="frequency" word="commitment" count="8"/>
 <result title="frequency" word="improved" count="8"/>
 <result title="frequency" word="individual" count="8"/>
 <result title="frequency" word="px;" count="8"/>
 <result title="frequency" word="{font-family" count="8"/>
 <result title="frequency" word="Aston" count="7"/>
 <result title="frequency" word="Jan" count="7"/>
 <result title="frequency" word="Qual" count="7"/>
 <result title="frequency" word="comparison" count="7"/>
 <result title="frequency" word="completed" count="7"/>
 <result title="frequency" word="components" count="7"/>
 <result title="frequency" word="font-size" count="7"/>
 <result title="frequency" word="healthcare" count="7"/>
 <result title="frequency" word="including" count="7"/>
 <result title="frequency" word="interventions" count="7"/>
 <result title="frequency" word="mental" count="7"/>
 <result title="frequency" word="practice" count="7"/>
 <result title="frequency" word="process" count="7"/>
 <result title="frequency" word="processes" count="7"/>
 <result title="frequency" word="study" count="7"/>
 <result title="frequency" word="team-based" count="7"/>
 <result title="frequency" word="training" count="7"/>
 <result title="frequency" word="B’s" count="6"/>
 <result title="frequency" word="Figure" count="6"/>
 <result title="frequency" word="Healthcare" count="6"/>
 <result title="frequency" word="National" count="6"/>
 <result title="frequency" word="Trusts" count="6"/>
 <result title="frequency" word="accessed" count="6"/>
 <result title="frequency" word="achieving" count="6"/>
 <result title="frequency" word="analysis" count="6"/>
 <result title="frequency" word="approach" count="6"/>
 <result title="frequency" word="change" count="6"/>
 <result title="frequency" word="changes" count="6"/>
 <result title="frequency" word="completion" count="6"/>
 <result title="frequency" word="current" count="6"/>
 <result title="frequency" word="data" count="6"/>
 <result title="frequency" word="double;" count="6"/>
 <result title="frequency" word="facilitation" count="6"/>
 <result title="frequency" word="innovation" count="6"/>
 <result title="frequency" word="leader" count="6"/>
 <result title="frequency" word="learning" count="6"/>
 <result title="frequency" word="longer" count="6"/>
 <result title="frequency" word="member" count="6"/>
 <result title="frequency" word="need" count="6"/>
 <result title="frequency" word="number" count="6"/>
 <result title="frequency" word="orthopaedic" count="6"/>
 <result title="frequency" word="problems" count="6"/>
 <result title="frequency" word="services" count="6"/>
 <result title="frequency" word="shared" count="6"/>
 <result title="frequency" word="task" count="6"/>
 <result title="frequency" word="tools" count="6"/>
 <result title="frequency" word="used" count="6"/>
 <result title="frequency" word="using" count="6"/>
 <result title="frequency" word="way" count="6"/>
 <result title="frequency" word="A’s" count="5"/>
 <result title="frequency" word="BMJ" count="5"/>
 <result title="frequency" word="Care" count="5"/>
 <result title="frequency" word="England," count="5"/>
 <result title="frequency" word="Group" count="5"/>
 <result title="frequency" word="Safety" count="5"/>
 <result title="frequency" word="achieved" count="5"/>
 <result title="frequency" word="baseline" count="5"/>
 <result title="frequency" word="border-color" count="5"/>
 <result title="frequency" word="border-width" count="5"/>
 <result title="frequency" word="coaching" count="5"/>
 <result title="frequency" word="comparable" count="5"/>
 <result title="frequency" word="conflict" count="5"/>
 <result title="frequency" word="dementia" count="5"/>
 <result title="frequency" word="effective" count="5"/>
 <result title="frequency" word="facilitator" count="5"/>
 <result title="frequency" word="findings" count="5"/>
 <result title="frequency" word="group" count="5"/>
 <result title="frequency" word="increased" count="5"/>
 <result title="frequency" word="inpatient" count="5"/>
 <result title="frequency" word="key" count="5"/>
 <result title="frequency" word="level" count="5"/>
 <result title="frequency" word="measurement" count="5"/>
 <result title="frequency" word="measurement," count="5"/>
 <result title="frequency" word="model" count="5"/>
 <result title="frequency" word="new" count="5"/>
 <result title="frequency" word="participation" count="5"/>
 <result title="frequency" word="perceived" count="5"/>
 <result title="frequency" word="presented" count="5"/>
 <result title="frequency" word="providing" count="5"/>
 <result title="frequency" word="reduction" count="5"/>
 <result title="frequency" word="safety" count="5"/>
 <result title="frequency" word="service" count="5"/>
 <result title="frequency" word="solid;" count="5"/>
 <result title="frequency" word="structured" count="5"/>
 <result title="frequency" word="successful" count="5"/>
 <result title="frequency" word="teams," count="5"/>
 <result title="frequency" word="teamworking" count="5"/>
 <result title="frequency" word="workshops" count="5"/>
 <result title="frequency" word="{font-style" count="5"/>
 <result title="frequency" word="{font-weight" count="5"/>
 <result title="frequency" word="(Team" count="4"/>
 <result title="frequency" word="(time" count="4"/>
 <result title="frequency" word="Fellowship" count="4"/>
 <result title="frequency" word="Service" count="4"/>
 <result title="frequency" word="Steering" count="4"/>
 <result title="frequency" word="West" count="4"/>
 <result title="frequency" word="approaches" count="4"/>
 <result title="frequency" word="assessment" count="4"/>
 <result title="frequency" word="bold" count="4"/>
 <result title="frequency" word="climate" count="4"/>
 <result title="frequency" word="collab:" count="4"/>
 <result title="frequency" word="complete" count="4"/>
 <result title="frequency" word="conflicts" count="4"/>
 <result title="frequency" word="consensus" count="4"/>
 <result title="frequency" word="courier;" count="4"/>
 <result title="frequency" word="diagrams" count="4"/>
 <result title="frequency" word="different" count="4"/>
 <result title="frequency" word="em;" count="4"/>
 <result title="frequency" word="evidence" count="4"/>
 <result title="frequency" word="included" count="4"/>
 <result title="frequency" word="itself" count="4"/>
 <result title="frequency" word="needed" count="4"/>
 <result title="frequency" word="organisations." count="4"/>
 <result title="frequency" word="overall" count="4"/>
 <result title="frequency" word="participated" count="4"/>
 <result title="frequency" word="performance," count="4"/>
 <result title="frequency" word="processes," count="4"/>
 <result title="frequency" word="project," count="4"/>
 <result title="frequency" word="projects." count="4"/>
 <result title="frequency" word="pt;}" count="4"/>
 <result title="frequency" word="ratings" count="4"/>
 <result title="frequency" word="recognition" count="4"/>
 <result title="frequency" word="research" count="4"/>
 <result title="frequency" word="satisfaction" count="4"/>
 <result title="frequency" word="scores;" count="4"/>
 <result title="frequency" word="showing" count="4"/>
 <result title="frequency" word="stages" count="4"/>
 <result title="frequency" word="start" count="4"/>
 <result title="frequency" word="stay" count="4"/>
 <result title="frequency" word="sustained" count="4"/>
 <result title="frequency" word="team," count="4"/>
 <result title="frequency" word="team." count="4"/>
 <result title="frequency" word="things" count="4"/>
 <result title="frequency" word="use" count="4"/>
 <result title="frequency" word="validated" count="4"/>
 <result title="frequency" word="year" count="4"/>
 <result title="frequency" word=" year" count="4"/>
</results>
