<?xml version="1.0" encoding="UTF-8"?>
<ref id="CR48" class="ref">
 <span class="label" xmlns="http://www.w3.org/1999/xhtml">48.</span>
 <element-citation publication-type="journal" class="element-citation">
  <person-group person-group-type="author" class="person-group">
   <name class="name">
    <span class="surname" xmlns="http://www.w3.org/1999/xhtml">Oris</span>
    <span class="given-names" xmlns="http://www.w3.org/1999/xhtml">F</span>
   </name>
   <span class="etal" xmlns="http://www.w3.org/1999/xhtml"/>
  </person-group>
  <div class="article-title" xmlns="http://www.w3.org/1999/xhtml">Effect of increased fire activity on global warming in the boreal forest</div>
  <div class="source" xmlns="http://www.w3.org/1999/xhtml">Environ. Rev.</div>
  <span class="year" xmlns="http://www.w3.org/1999/xhtml">2014</span>
  <span class="volume" xmlns="http://www.w3.org/1999/xhtml">22</span>
  <span class="fpage" xmlns="http://www.w3.org/1999/xhtml">206</span>
  <span class="lpage" xmlns="http://www.w3.org/1999/xhtml">219</span>
  <span pub-id-type="doi" class="pub-id" xmlns="http://www.w3.org/1999/xhtml">10.1139/er-2013-0062</span>
 </element-citation>
</ref>
