<?xml version="1.0" encoding="UTF-8"?>
<ref id="pone.0202877.ref011" class="ref">
 <span class="label" xmlns="http://www.w3.org/1999/xhtml">11</span>
 <div publication-type="journal" class="mixed-citation" xmlns="http://www.w3.org/1999/xhtml">
  <name class="name" xmlns="">
   <span class="surname" xmlns="http://www.w3.org/1999/xhtml">Kahan</span>
   <span class="given-names" xmlns="http://www.w3.org/1999/xhtml">D.</span>
  </name>
  <div class="article-title">Why we are poles apart on climate change</div>. 
  <div class="source">Nature</div>. 
  <span class="year">2012</span>;
  <span class="volume">488</span>(
  <span class="issue">7411</span>):
  <span class="fpage">255</span> Epub 2012/08/17. 
  <span pub-id-type="doi" class="pub-id">10.1038/488255a</span>
  <?supplied-pmid 22895298?>
  <span pub-id-type="pmid" class="pub-id">22895298</span>
 </div>
</ref>
