{
  "id": [
    "30333710"
  ],
  "source": [
    "MED"
  ],
  "pmid": [
    "30333710"
  ],
  "pmcid": [
    "PMC6189584"
  ],
  "doi": [
    "10.1098/rspa.2018.0351"
  ],
  "title": [
    "Control and prediction of the organic solid state: a challenge to theory and experiment†."
  ],
  "authorString": [
    "Price SL."
  ],
  "authorList": [
    {
      "author": [
        {
          "fullName": [
            "Price SL"
          ],
          "firstName": [
            "Sarah L"
          ],
          "lastName": [
            "Price"
          ],
          "initials": [
            "SL"
          ],
          "authorId": [
            {
              "_": "0000-0002-1230-7427",
              "$": {
                "type": "ORCID"
              }
            }
          ],
          "affiliation": [
            "Department of Chemistry, University College London, 20 Gordon St, London WC1H 0AJ, UK."
          ]
        }
      ]
    }
  ],
  "authorIdList": [
    {
      "authorId": [
        {
          "_": "0000-0002-1230-7427",
          "$": {
            "type": "ORCID"
          }
        }
      ]
    }
  ],
  "journalInfo": [
    {
      "issue": [
        "2217"
      ],
      "volume": [
        "474"
      ],
      "journalIssueId": [
        "2740105"
      ],
      "dateOfPublication": [
        "2018 Sep"
      ],
      "monthOfPublication": [
        "9"
      ],
      "yearOfPublication": [
        "2018"
      ],
      "printPublicationDate": [
        "2018-09-01"
      ],
      "journal": [
        {
          "title": [
            "Proceedings. Mathematical, physical, and engineering sciences"
          ],
          "ISOAbbreviation": [
            "Proc. Math. Phys. Eng. Sci."
          ],
          "medlineAbbreviation": [
            "Proc Math Phys Eng Sci"
          ],
          "NLMid": [
            "9891746"
          ],
          "ISSN": [
            "1364-5021"
          ],
          "ESSN": [
            "1471-2946"
          ]
        }
      ]
    }
  ],
  "pubYear": [
    "2018"
  ],
  "pageInfo": [
    "20180351"
  ],
  "abstractText": [
    "The ability of theoretical chemists to quantitatively model the weak forces between organic molecules is being exploited to predict their crystal structures and estimate their physical properties. Evolving crystal structure prediction methods are increasingly being used to aid the design of organic functional materials and provide information about thermodynamically plausible polymorphs of speciality organic materials to aid, for example, pharmaceutical development. However, the increasingly sophisticated experimental studies for detecting the range of organic solid-state behaviours provide many challenges for improving quantitative theories that form the basis for the computer modelling. It is challenging to calculate the relative thermodynamic stability of different organic crystal structures, let alone understand the kinetic effects that determine which polymorphs can be observed and are practically important. However, collaborations between experiment and theory are reaching the stage of devising experiments to target the first crystallization of new polymorphs or create novel organic molecular materials."
  ],
  "affiliation": [
    "Department of Chemistry, University College London, 20 Gordon St, London WC1H 0AJ, UK."
  ],
  "language": [
    "eng"
  ],
  "pubModel": [
    "Print-Electronic"
  ],
  "pubTypeList": [
    {
      "pubType": [
        "review-article",
        "Review",
        "Journal Article"
      ]
    }
  ],
  "grantsList": [
    {
      "grant": [
        {
          "grantId": [
            "EP/K039229/1"
          ],
          "agency": [
            "Engineering and Physical Sciences Research Council"
          ],
          "orderIn": [
            "0"
          ]
        },
        {
          "grantId": [
            "EP/F03573X/1"
          ],
          "agency": [
            "Engineering and Physical Sciences Research Council"
          ],
          "orderIn": [
            "0"
          ]
        }
      ]
    }
  ],
  "keywordList": [
    {
      "keyword": [
        "Polymorphism",
        "Pharmaceutical Development",
        "Organic Crystal Structures",
        "Theoretical Prediction"
      ]
    }
  ],
  "fullTextUrlList": [
    {
      "fullTextUrl": [
        {
          "availability": [
            "Open access"
          ],
          "availabilityCode": [
            "OA"
          ],
          "documentStyle": [
            "pdf"
          ],
          "site": [
            "Europe_PMC"
          ],
          "url": [
            "http://europepmc.org/articles/PMC6189584?pdf=render"
          ]
        },
        {
          "availability": [
            "Open access"
          ],
          "availabilityCode": [
            "OA"
          ],
          "documentStyle": [
            "html"
          ],
          "site": [
            "Europe_PMC"
          ],
          "url": [
            "http://europepmc.org/articles/PMC6189584"
          ]
        },
        {
          "availability": [
            "Subscription required"
          ],
          "availabilityCode": [
            "S"
          ],
          "documentStyle": [
            "doi"
          ],
          "site": [
            "DOI"
          ],
          "url": [
            "https://doi.org/10.1098/rspa.2018.0351"
          ]
        }
      ]
    }
  ],
  "isOpenAccess": [
    "Y"
  ],
  "inEPMC": [
    "Y"
  ],
  "inPMC": [
    "N"
  ],
  "hasPDF": [
    "Y"
  ],
  "hasBook": [
    "N"
  ],
  "hasSuppl": [
    "N"
  ],
  "citedByCount": [
    "0"
  ],
  "hasReferences": [
    "Y"
  ],
  "hasTextMinedTerms": [
    "Y"
  ],
  "hasDbCrossReferences": [
    "N"
  ],
  "hasLabsLinks": [
    "Y"
  ],
  "license": [
    "cc by"
  ],
  "authMan": [
    "N"
  ],
  "epmcAuthMan": [
    "N"
  ],
  "nihAuthMan": [
    "N"
  ],
  "hasTMAccessionNumbers": [
    "N"
  ],
  "dateOfCreation": [
    "2018-10-19"
  ],
  "firstIndexDate": [
    "2018-10-19"
  ],
  "dateOfRevision": [
    "2018-10-21"
  ],
  "electronicPublicationDate": [
    "2018-09-19"
  ],
  "firstPublicationDate": [
    "2018-09-19"
  ]
}