<?xml version="1.0" encoding="UTF-8"?>
<ref id="pone.0136385.ref004" class="ref">
 <label class="label">4</label>
 <mixed-citation publication-type="book" class="mixed-citation">
  <collab class="collab">Intergovernmental Panel on Climate Change</collab>. 
  <chapter-title class="chapter-title">Climate Change 2007: The scientific basis</chapter-title> In: 
  <name class="name">
   <surname class="surname">Solomon</surname>
   <given-names class="given-names">S</given-names>
  </name>, 
  <name class="name">
   <surname class="surname">Qin</surname>
   <given-names class="given-names">D</given-names>
  </name>, 
  <name class="name">
   <surname class="surname">Manning</surname>
   <given-names class="given-names">M</given-names>
  </name>, 
  <name class="name">
   <surname class="surname">Chen</surname>
   <given-names class="given-names">Z</given-names>
  </name>, 
  <name class="name">
   <surname class="surname">Marquis</surname>
   <given-names class="given-names">MC</given-names>
  </name>, 
  <name class="name">
   <surname class="surname">Averyt</surname>
   <given-names class="given-names">K</given-names>
  </name>, 
  <name class="name">
   <surname class="surname">Tignor</surname>
   <given-names class="given-names">M</given-names>
  </name>, 
  <name class="name">
   <surname class="surname">Miller</surname>
   <given-names class="given-names">HL</given-names>
  </name>, editors. 
  <source class="source">Contributions of Working Group I to the Fourth Assessment Report of the Intergovernmental Panel on Climate Change: The Physical Science Basis</source>. 
  <publisher-loc class="publisher-loc">Cambridge</publisher-loc>: 
  <publisher-name class="publisher-name">Cambridge University Press</publisher-name>; 
  <year class="year">2007</year> pp. 
  <fpage class="fpage">1</fpage>–
  <lpage class="lpage">18</lpage>.
 </mixed-citation>
</ref>
