<?xml version="1.0" encoding="UTF-8"?>
<contrib id="evo12635-cr-0002" contrib-type="author" class="contrib">
 <name class="name">
  <span class="surname" xmlns="http://www.w3.org/1999/xhtml">Hoyle</span>
  <span class="given-names" xmlns="http://www.w3.org/1999/xhtml">Rebecca B.</span>
 </name>
 <div class="address" xmlns="http://www.w3.org/1999/xhtml">
  <span class="email">r.b.hoyle@soton.ac.uk</span>
 </div>
 <a ref-type="aff" rid="evo12635-aff-0004" href="#evo12635-aff-0004" xmlns="http://www.w3.org/1999/xhtml">
  <span class="sup">4</span>
 </a>
 <a ref-type="aff" rid="evo12635-aff-0005" href="#evo12635-aff-0005" xmlns="http://www.w3.org/1999/xhtml">
  <span class="sup">5</span>
 </a>
</contrib>
