<?xml version="1.0" encoding="UTF-8"?>
<ref id="pone.0029329-Sun1" class="ref">
 <span class="label" xmlns="http://www.w3.org/1999/xhtml">64</span>
 <element-citation publication-type="journal" class="element-citation">
  <person-group person-group-type="author" class="person-group">
   <name class="name">
    <span class="surname" xmlns="http://www.w3.org/1999/xhtml">Sun</span>
    <span class="given-names" xmlns="http://www.w3.org/1999/xhtml">BN</span>
   </name>
   <name class="name">
    <span class="surname" xmlns="http://www.w3.org/1999/xhtml">Wu</span>
    <span class="given-names" xmlns="http://www.w3.org/1999/xhtml">JY</span>
   </name>
   <name class="name">
    <span class="surname" xmlns="http://www.w3.org/1999/xhtml">Liu</span>
    <span class="given-names" xmlns="http://www.w3.org/1999/xhtml">YSC</span>
   </name>
   <name class="name">
    <span class="surname" xmlns="http://www.w3.org/1999/xhtml">Ding</span>
    <span class="given-names" xmlns="http://www.w3.org/1999/xhtml">ST</span>
   </name>
   <name class="name">
    <span class="surname" xmlns="http://www.w3.org/1999/xhtml">Li</span>
    <span class="given-names" xmlns="http://www.w3.org/1999/xhtml">XC</span>
   </name>
  </person-group>
  <span class="year" xmlns="http://www.w3.org/1999/xhtml">2011</span>
  <div class="article-title" xmlns="http://www.w3.org/1999/xhtml">Reconstructing Neogene vegetation and climates to infer tectonic uplift in western Yunnan, China.</div>
  <div class="source" xmlns="http://www.w3.org/1999/xhtml">Palaeogeography, Palaeoclimatology, Palaeoecology</div>
  <span class="volume" xmlns="http://www.w3.org/1999/xhtml">304</span>
  <span class="fpage" xmlns="http://www.w3.org/1999/xhtml">328</span>
  <span class="lpage" xmlns="http://www.w3.org/1999/xhtml">336</span>
 </element-citation>
</ref>
