<?xml version="1.0" encoding="UTF-8"?>
<contrib-group class="contrib-group">
 <contrib contrib-type="author" corresp="yes" class="contrib">
  <name class="name">
   <surname class="surname">Lake</surname>
   <given-names class="given-names">Iain R.</given-names>
  </name>
  <address class="address">
   <phone class="phone">+44 1603 593744</phone>
   <email class="email">I.Lake@uea.ac.uk</email>
  </address>
  <xref ref-type="aff" rid="Aff1" class="xref"/>
 </contrib>
 <aff id="Aff1" class="aff">
  <institution-wrap class="institution-wrap">
   <institution-id institution-id-type="ISNI" class="institution-id">0000 0001 1092 7967</institution-id>
   <institution-id institution-id-type="GRID" class="institution-id">grid.8273.e</institution-id>
   <institution class="institution">School of Environmental Sciences, </institution>
   <institution class="institution">University of East Anglia, </institution>
  </institution-wrap>Norwich, NR4 7TJ UK 
 </aff>
</contrib-group>
