<?xml version="1.0" encoding="UTF-8"?>
<ref id="B65-biology-01-00411" class="ref">
 <span class="label" xmlns="http://www.w3.org/1999/xhtml">65.</span>
 <element-citation publication-type="journal" class="element-citation">
  <person-group person-group-type="author" class="person-group">
   <name class="name">
    <span class="surname" xmlns="http://www.w3.org/1999/xhtml">Fletcher</span>
    <span class="given-names" xmlns="http://www.w3.org/1999/xhtml">M.G.</span>
   </name>
   <name class="name">
    <span class="surname" xmlns="http://www.w3.org/1999/xhtml">Axtell</span>
    <span class="given-names" xmlns="http://www.w3.org/1999/xhtml">R.C.</span>
   </name>
   <name class="name">
    <span class="surname" xmlns="http://www.w3.org/1999/xhtml">Stinner</span>
    <span class="given-names" xmlns="http://www.w3.org/1999/xhtml">R.E.</span>
   </name>
  </person-group>
  <div class="article-title" xmlns="http://www.w3.org/1999/xhtml">Longevity and fecundity of 
   <span class="italic">Musca domestica</span> (Diptera, Muscidae) as a function of temperature
  </div>
  <div class="source" xmlns="http://www.w3.org/1999/xhtml">J. Med. Entomol.</div>
  <span class="year" xmlns="http://www.w3.org/1999/xhtml">1990</span>
  <span class="volume" xmlns="http://www.w3.org/1999/xhtml">27</span>
  <span class="fpage" xmlns="http://www.w3.org/1999/xhtml">922</span>
  <span class="lpage" xmlns="http://www.w3.org/1999/xhtml">926</span>
  <span pub-id-type="pmid" class="pub-id" xmlns="http://www.w3.org/1999/xhtml">2231628</span>
 </element-citation>
</ref>
