<?xml version="1.0" encoding="UTF-8"?>
<ref id="B8-tropicalmed-03-00117" class="ref">
 <span class="label" xmlns="http://www.w3.org/1999/xhtml">8.</span>
 <element-citation publication-type="journal" class="element-citation">
  <person-group person-group-type="author" class="person-group">
   <name class="name">
    <span class="surname" xmlns="http://www.w3.org/1999/xhtml">Hay</span>
    <span class="given-names" xmlns="http://www.w3.org/1999/xhtml">S.I.</span>
   </name>
   <name class="name">
    <span class="surname" xmlns="http://www.w3.org/1999/xhtml">Abajobir</span>
    <span class="given-names" xmlns="http://www.w3.org/1999/xhtml">A.A.</span>
   </name>
   <name class="name">
    <span class="surname" xmlns="http://www.w3.org/1999/xhtml">Abate</span>
    <span class="given-names" xmlns="http://www.w3.org/1999/xhtml">K.H.</span>
   </name>
   <name class="name">
    <span class="surname" xmlns="http://www.w3.org/1999/xhtml">Abbafati</span>
    <span class="given-names" xmlns="http://www.w3.org/1999/xhtml">C.</span>
   </name>
   <name class="name">
    <span class="surname" xmlns="http://www.w3.org/1999/xhtml">Abbas</span>
    <span class="given-names" xmlns="http://www.w3.org/1999/xhtml">K.M.</span>
   </name>
   <name class="name">
    <span class="surname" xmlns="http://www.w3.org/1999/xhtml">Abd-Allah</span>
    <span class="given-names" xmlns="http://www.w3.org/1999/xhtml">F.</span>
   </name>
   <name class="name">
    <span class="surname" xmlns="http://www.w3.org/1999/xhtml">Abdulkader</span>
    <span class="given-names" xmlns="http://www.w3.org/1999/xhtml">R.S.</span>
   </name>
   <name class="name">
    <span class="surname" xmlns="http://www.w3.org/1999/xhtml">Abdulle</span>
    <span class="given-names" xmlns="http://www.w3.org/1999/xhtml">A.M.</span>
   </name>
   <name class="name">
    <span class="surname" xmlns="http://www.w3.org/1999/xhtml">Abebo</span>
    <span class="given-names" xmlns="http://www.w3.org/1999/xhtml">T.A.</span>
   </name>
   <name class="name">
    <span class="surname" xmlns="http://www.w3.org/1999/xhtml">Abera</span>
    <span class="given-names" xmlns="http://www.w3.org/1999/xhtml">S.F.</span>
   </name>
   <span class="etal" xmlns="http://www.w3.org/1999/xhtml"/>
  </person-group>
  <div class="article-title" xmlns="http://www.w3.org/1999/xhtml">Global, regional, and national disability-adjusted life-years (DALYs) for 333 diseases and injuries and healthy life expectancy (HALE) for 195 countries and territories, 1990–2016: A systematic analysis for the Global Burden of Disease Study 2016</div>
  <div class="source" xmlns="http://www.w3.org/1999/xhtml">Lancet</div>
  <span class="year" xmlns="http://www.w3.org/1999/xhtml">2017</span>
  <span class="volume" xmlns="http://www.w3.org/1999/xhtml">39010100</span>
  <span class="fpage" xmlns="http://www.w3.org/1999/xhtml">1260</span>
  <span class="lpage" xmlns="http://www.w3.org/1999/xhtml">1344</span>
  <span pub-id-type="doi" class="pub-id" xmlns="http://www.w3.org/1999/xhtml">10.1016/S0140-6736(17)32130-X</span>
 </element-citation>
</ref>
