<?xml version="1.0" encoding="UTF-8"?>
<ref id="ece33405-bib-0042" class="ref">
 <div publication-type="journal" id="ece33405-cit-0042" class="mixed-citation" xmlns="http://www.w3.org/1999/xhtml">
  <div class="string-name">
   <span class="surname">Ma</span>, 
   <span class="given-names">W. Y.</span>
  </div> (
  <span class="year">1989</span>). 
  <div class="article-title">Masked laughingthrush's habits and the roles in preying on pine moth</div>. 
  <div class="source">Hunan Forestry Science and Technology</div>, 
  <span class="volume">1989</span>(
  <span class="issue">3</span>), 
  <span class="fpage">36</span>–
  <span class="lpage">37</span>.
 </div>
</ref>
