<?xml version="1.0" encoding="UTF-8"?>
<ref id="B93" class="ref">
 <div publication-type="journal" class="mixed-citation" xmlns="http://www.w3.org/1999/xhtml">
  <name class="name" xmlns="">
   <span class="surname" xmlns="http://www.w3.org/1999/xhtml">Hemmersbach-Miller</span>
   <span class="given-names" xmlns="http://www.w3.org/1999/xhtml">M</span>
  </name>
  <name class="name" xmlns="">
   <span class="surname" xmlns="http://www.w3.org/1999/xhtml">Parola</span>
   <span class="given-names" xmlns="http://www.w3.org/1999/xhtml">P</span>
  </name>
  <name class="name" xmlns="">
   <span class="surname" xmlns="http://www.w3.org/1999/xhtml">Brouqui</span>
   <span class="given-names" xmlns="http://www.w3.org/1999/xhtml">P</span>
  </name>
  <name class="name" xmlns="">
   <span class="surname" xmlns="http://www.w3.org/1999/xhtml">Raoult</span>
   <span class="given-names" xmlns="http://www.w3.org/1999/xhtml">D</span>
  </name>
  <div class="article-title">A 51-year-old homeless man who died in Marseille, southern France</div>
  <div class="source">Clin Infect Dis</div>
  <span class="year">2004</span>
  <span class="volume">38</span>
  <span class="fpage">1412</span>
  <span class="lpage">1493</span>
  <?supplied-pmid 15164735?>
  <span pub-id-type="pmid" class="pub-id">15164735</span>
 </div>
</ref>
